pyghgaq/__init__.py
pyghgaq/main.py
pyghgaq/data/constant.yml
pyghgaq/functions/__init__.py
pyghgaq/functions/functions.py
pyghgaq/functions/k600_functions.py
pyghgaq/functions/read.py
pyghgaq/functions/type_utils.py
pyghgaq/functions/units.py
pyghgaq/gases/CH4.py
pyghgaq/gases/CO2.py
pyghgaq/gases/__init__.py
pyghgaq/registry/registry.py
pyghgaq-0.1.2.dist-info/METADATA
pyghgaq-0.1.2.dist-info/WHEEL
pyghgaq-0.1.2.dist-info/licenses/LICENCE
pyghgaq-0.1.2.dist-info/RECORD
