Metadata-Version: 2.4
Name: pyghgaq
Version: 0.1.2
Summary: A package to calculate GHG emissions from aquatic ecosystems
Project-URL: Homepage, https://github.com/ceordonez/PyGHGaq
Project-URL: Issues, https://github.com/ceordonez/PyGHGaq/issues
Author-email: César Ordóñez <cesar.ordonez@unige.ch>
License-Expression: MIT
License-File: LICENCE
Classifier: Operating System :: OS Independent
Classifier: Programming Language :: Python :: 3
Requires-Python: >=3.12
Requires-Dist: numpy
Requires-Dist: pandas
Requires-Dist: pint
Requires-Dist: pyyaml
